{"id": "XzKZkwEACAAJ", "title": "Look Out, Secret Seven", "subtitle": null, "authors": ["Enid Blyton", "Tony Ross"], "publisher": null, "publishedDate": "2013", "description": "What would the Seven do without Scamper the spaniel? First he discovers an unwanted visitor - then he protects the Seven as they spy on a thief late at night in Bramley Woods.", "industryIdentifiers": [{"type": "ISBN_10", "identifier": "1444913565"}, {"type": "ISBN_13", "identifier": "9781444913569"}], "pageCount": 130, "printType": ["Audiobook", "Paperback"], "categories": ["Adventure stories", "Adventure"], "imageLinks": {"smallThumbnail": "http://books.google.com/books/content?id=XzKZkwEACAAJ&printsec=frontcover&img=1&zoom=5&source=public", "thumbnail": "http://books.google.com/books/content?id=XzKZkwEACAAJ&printsec=frontcover&img=1&zoom=1&source=public"}, "language": "en", "deliveryOption": "super fast", "price": 23}